StreamSYS/StreamSYS.py
StreamSYS/__init__.py
StreamSYS/client.py
StreamSYS/loader.py
streamsys-1.1.46.dist-info/METADATA
streamsys-1.1.46.dist-info/WHEEL
streamsys-1.1.46.dist-info/top_level.txt
streamsys-1.1.46.dist-info/RECORD
